odoo/addons/l10n_ro_siruta/README.rst
odoo/addons/l10n_ro_siruta/__init__.py
odoo/addons/l10n_ro_siruta/__manifest__.py
odoo/addons/l10n_ro_siruta/hooks.py
odoo/addons/l10n_ro_siruta/data/res.country.commune.csv
odoo/addons/l10n_ro_siruta/data/res.country.state.csv
odoo/addons/l10n_ro_siruta/data/res.country.zone.csv
odoo/addons/l10n_ro_siruta/demo/demo_siruta.xml
odoo/addons/l10n_ro_siruta/i18n/l10n_ro_siruta.pot
odoo/addons/l10n_ro_siruta/i18n/ro.po
odoo/addons/l10n_ro_siruta/models/__init__.py
odoo/addons/l10n_ro_siruta/models/res_partner.py
odoo/addons/l10n_ro_siruta/models/siruta.py
odoo/addons/l10n_ro_siruta/readme/CONTRIBUTORS.rst
odoo/addons/l10n_ro_siruta/readme/DESCRIPTION.rst
odoo/addons/l10n_ro_siruta/readme/INSTALL.rst
odoo/addons/l10n_ro_siruta/readme/USAGE.rst
odoo/addons/l10n_ro_siruta/security/ir.model.access.csv
odoo/addons/l10n_ro_siruta/static/description/address.png
odoo/addons/l10n_ro_siruta/static/description/customer.png
odoo/addons/l10n_ro_siruta/static/description/icon.png
odoo/addons/l10n_ro_siruta/static/description/index.html
odoo/addons/l10n_ro_siruta/static/src/less/form_view.less
odoo/addons/l10n_ro_siruta/tests/__init__.py
odoo/addons/l10n_ro_siruta/tests/test_siruta.py
odoo/addons/l10n_ro_siruta/views/assets.xml
odoo/addons/l10n_ro_siruta/views/partner_view.xml
odoo/addons/l10n_ro_siruta/views/siruta_view.xml
odoo13_addon_l10n_ro_siruta-13.0.1.0.1.dev23.dist-info/METADATA
odoo13_addon_l10n_ro_siruta-13.0.1.0.1.dev23.dist-info/WHEEL
odoo13_addon_l10n_ro_siruta-13.0.1.0.1.dev23.dist-info/top_level.txt
odoo13_addon_l10n_ro_siruta-13.0.1.0.1.dev23.dist-info/RECORD
